[
    {
        "id": "bitcoin", 
        "name": "Bitcoin", 
        "symbol": "BTC", 
        "rank": "1", 
        "price_usd": "9338.6", 
        "price_btc": "1.0", 
        "24h_volume_usd": "8814330000.0", 
        "market_cap_usd": "158810597345", 
        "available_supply": "17005825.0", 
        "total_supply": "17005825.0", 
        "max_supply": "21000000.0", 
        "percent_change_1h": "-0.12", 
        "percent_change_24h": "-0.33", 
        "percent_change_7d": "5.02", 
        "last_updated": "1525032874"
    }, 
    {
        "id": "ethereum", 
        "name": "Ethereum", 
        "symbol": "ETH", 
        "rank": "2", 
        "price_usd": "680.611", 
        "price_btc": "0.0730819", 
        "24h_volume_usd": "2717070000.0", 
        "market_cap_usd": "67467029432.0", 
        "available_supply": "99127151.0", 
        "total_supply": "99127151.0", 
        "max_supply": null, 
        "percent_change_1h": "-0.04", 
        "percent_change_24h": "-0.73", 
        "percent_change_7d": "7.42", 
        "last_updated": "1525032860"
    }, 
    {
        "id": "ripple", 
        "name": "Ripple", 
        "symbol": "XRP", 
        "rank": "3", 
        "price_usd": "0.860723", 
        "price_btc": "0.00009242", 
        "24h_volume_usd": "891558000.0", 
        "market_cap_usd": "33694037627.0", 
        "available_supply": "39146203398.0", 
        "total_supply": "99992334929.0", 
        "max_supply": "100000000000", 
        "percent_change_1h": "-0.37", 
        "percent_change_24h": "-1.5", 
        "percent_change_7d": "-2.84", 
        "last_updated": "1525032841"
    }, 
    {
        "id": "bitcoin-cash", 
        "name": "Bitcoin Cash", 
        "symbol": "BCH", 
        "rank": "4", 
        "price_usd": "1430.24", 
        "price_btc": "0.153575", 
        "24h_volume_usd": "1045340000.0", 
        "market_cap_usd": "24458248192.0", 
        "available_supply": "17100800.0", 
        "total_supply": "17100800.0", 
        "max_supply": "21000000.0", 
        "percent_change_1h": "-0.32", 
        "percent_change_24h": "1.95", 
        "percent_change_7d": "16.11", 
        "last_updated": "1525032855"
    }, 
    {
        "id": "eos", 
        "name": "EOS", 
        "symbol": "EOS", 
        "rank": "5", 
        "price_usd": "20.8467", 
        "price_btc": "0.00223845", 
        "24h_volume_usd": "4675410000.0", 
        "market_cap_usd": "17195436919.0", 
        "available_supply": "824851747.0", 
        "total_supply": "900000000.0", 
        "max_supply": "1000000000.0", 
        "percent_change_1h": "1.19", 
        "percent_change_24h": "9.15", 
        "percent_change_7d": "80.82", 
        "last_updated": "1525032854"
    }, 
    {
        "id": "cardano", 
        "name": "Cardano", 
        "symbol": "ADA", 
        "rank": "6", 
        "price_usd": "0.368985", 
        "price_btc": "0.00003962", 
        "24h_volume_usd": "713232000.0", 
        "market_cap_usd": "9566700122.0", 
        "available_supply": "25927070538.0", 
        "total_supply": "31112483745.0", 
        "max_supply": "45000000000.0", 
        "percent_change_1h": "-0.02", 
        "percent_change_24h": "4.19", 
        "percent_change_7d": "27.43", 
        "last_updated": "1525032858"
    }, 
    {
        "id": "litecoin", 
        "name": "Litecoin", 
        "symbol": "LTC", 
        "rank": "7", 
        "price_usd": "151.638", 
        "price_btc": "0.0162824", 
        "24h_volume_usd": "378988000.0", 
        "market_cap_usd": "8538309321.0", 
        "available_supply": "56307188.0", 
        "total_supply": "56307188.0", 
        "max_supply": "84000000.0", 
        "percent_change_1h": "-0.46", 
        "percent_change_24h": "-0.62", 
        "percent_change_7d": "1.61", 
        "last_updated": "1525032842"
    }, 
    {
        "id": "stellar", 
        "name": "Stellar", 
        "symbol": "XLM", 
        "rank": "8", 
        "price_usd": "0.447496", 
        "price_btc": "0.00004805", 
        "24h_volume_usd": "155206000.0", 
        "market_cap_usd": "8310561194.0", 
        "available_supply": "18571252468.0", 
        "total_supply": "103887050716", 
        "max_supply": null, 
        "percent_change_1h": "0.16", 
        "percent_change_24h": "3.35", 
        "percent_change_7d": "19.56", 
        "last_updated": "1525032844"
    }, 
    {
        "id": "neo", 
        "name": "NEO", 
        "symbol": "NEO", 
        "rank": "9", 
        "price_usd": "87.7232", 
        "price_btc": "0.00941944", 
        "24h_volume_usd": "424665000.0", 
        "market_cap_usd": "5702008000.0", 
        "available_supply": "65000000.0", 
        "total_supply": "100000000.0", 
        "max_supply": "100000000.0", 
        "percent_change_1h": "0.3", 
        "percent_change_24h": "13.67", 
        "percent_change_7d": "16.68", 
        "last_updated": "1525032850"
    }, 
    {
        "id": "tron", 
        "name": "TRON", 
        "symbol": "TRX", 
        "rank": "10", 
        "price_usd": "0.0858888", 
        "price_btc": "0.00000922", 
        "24h_volume_usd": "1099180000.0", 
        "market_cap_usd": "5647026411.0", 
        "available_supply": "65748111645.0", 
        "total_supply": "100000000000", 
        "max_supply": null, 
        "percent_change_1h": "0.28", 
        "percent_change_24h": "4.32", 
        "percent_change_7d": "60.64", 
        "last_updated": "1525032857"
    }, 
    {
        "id": "iota", 
        "name": "IOTA", 
        "symbol": "MIOTA", 
        "rank": "11", 
        "price_usd": "2.03159", 
        "price_btc": "0.00021815", 
        "24h_volume_usd": "80889600.0", 
        "market_cap_usd": "5646865928.0", 
        "available_supply": "2779530283.0", 
        "total_supply": "2779530283.0", 
        "max_supply": "2779530283.0", 
        "percent_change_1h": "0.39", 
        "percent_change_24h": "-0.46", 
        "percent_change_7d": "-0.67", 
        "last_updated": "1525032854"
    }, 
    {
        "id": "monero", 
        "name": "Monero", 
        "symbol": "XMR", 
        "rank": "12", 
        "price_usd": "251.086", 
        "price_btc": "0.0269608", 
        "24h_volume_usd": "95858600.0", 
        "market_cap_usd": "4012582721.0", 
        "available_supply": "15980910.0", 
        "total_supply": "15980910.0", 
        "max_supply": null, 
        "percent_change_1h": "-0.3", 
        "percent_change_24h": "-3.17", 
        "percent_change_7d": "-9.03", 
        "last_updated": "1525032843"
    }, 
    {
        "id": "dash", 
        "name": "Dash", 
        "symbol": "DASH", 
        "rank": "13", 
        "price_usd": "490.073", 
        "price_btc": "0.0526225", 
        "24h_volume_usd": "97310000.0", 
        "market_cap_usd": "3938910094.0", 
        "available_supply": "8037395.0", 
        "total_supply": "8037395.0", 
        "max_supply": "18900000.0", 
        "percent_change_1h": "0.26", 
        "percent_change_24h": "-1.28", 
        "percent_change_7d": "4.71", 
        "last_updated": "1525032842"
    }, 
    {
        "id": "nem", 
        "name": "NEM", 
        "symbol": "XEM", 
        "rank": "14", 
        "price_usd": "0.421091", 
        "price_btc": "0.00004522", 
        "24h_volume_usd": "46269800.0", 
        "market_cap_usd": "3789819000.0", 
        "available_supply": "8999999999.0", 
        "total_supply": "8999999999.0", 
        "max_supply": null, 
        "percent_change_1h": "0.04", 
        "percent_change_24h": "0.1", 
        "percent_change_7d": "7.21", 
        "last_updated": "1525032846"
    }, 
    {
        "id": "vechain", 
        "name": "VeChain", 
        "symbol": "VEN", 
        "rank": "15", 
        "price_usd": "4.67443", 
        "price_btc": "0.00050193", 
        "24h_volume_usd": "161520000.0", 
        "market_cap_usd": "2457717775.0", 
        "available_supply": "525779138.0", 
        "total_supply": "873378637.0", 
        "max_supply": null, 
        "percent_change_1h": "-1.54", 
        "percent_change_24h": "9.78", 
        "percent_change_7d": "19.62", 
        "last_updated": "1525032856"
    }, 
    {
        "id": "tether", 
        "name": "Tether", 
        "symbol": "USDT", 
        "rank": "16", 
        "price_usd": "1.00077", 
        "price_btc": "0.00010746", 
        "24h_volume_usd": "5111110000.0", 
        "market_cap_usd": "2419002012.0", 
        "available_supply": "2417140814.0", 
        "total_supply": "2580109970.0", 
        "max_supply": null, 
        "percent_change_1h": "0.24", 
        "percent_change_24h": "0.13", 
        "percent_change_7d": "0.2", 
        "last_updated": "1525032847"
    }, 
    {
        "id": "ethereum-classic", 
        "name": "Ethereum Classic", 
        "symbol": "ETC", 
        "rank": "17", 
        "price_usd": "21.549", 
        "price_btc": "0.00231386", 
        "24h_volume_usd": "258823000.0", 
        "market_cap_usd": "2185964844.0", 
        "available_supply": "101441591.0", 
        "total_supply": "101441591.0", 
        "max_supply": null, 
        "percent_change_1h": "0.64", 
        "percent_change_24h": "-1.37", 
        "percent_change_7d": "12.67", 
        "last_updated": "1525032849"
    }, 
    {
        "id": "qtum", 
        "name": "Qtum", 
        "symbol": "QTUM", 
        "rank": "18", 
        "price_usd": "22.5141", 
        "price_btc": "0.0024175", 
        "24h_volume_usd": "340560000.0", 
        "market_cap_usd": "1993825642.0", 
        "available_supply": "88558976.0", 
        "total_supply": "100558976.0", 
        "max_supply": null, 
        "percent_change_1h": "-0.06", 
        "percent_change_24h": "2.48", 
        "percent_change_7d": "13.76", 
        "last_updated": "1525032853"
    }, 
    {
        "id": "omisego", 
        "name": "OmiseGO", 
        "symbol": "OMG", 
        "rank": "19", 
        "price_usd": "17.9596", 
        "price_btc": "0.00192845", 
        "24h_volume_usd": "92438100.0", 
        "market_cap_usd": "1832643413.0", 
        "available_supply": "102042552.0", 
        "total_supply": "140245398.0", 
        "max_supply": null, 
        "percent_change_1h": "-1.01", 
        "percent_change_24h": "-0.8", 
        "percent_change_7d": "15.65", 
        "last_updated": "1525032855"
    }, 
    {
        "id": "icon", 
        "name": "ICON", 
        "symbol": "ICX", 
        "rank": "20", 
        "price_usd": "4.60373", 
        "price_btc": "0.00049433", 
        "24h_volume_usd": "108728000.0", 
        "market_cap_usd": "1782708576.0", 
        "available_supply": "387231348.0", 
        "total_supply": "400228740.0", 
        "max_supply": null, 
        "percent_change_1h": "0.03", 
        "percent_change_24h": "-4.89", 
        "percent_change_7d": "32.27", 
        "last_updated": "1525032859"
    }, 
    {
        "id": "binance-coin", 
        "name": "Binance Coin", 
        "symbol": "BNB", 
        "rank": "21", 
        "price_usd": "14.8008", 
        "price_btc": "0.00158927", 
        "24h_volume_usd": "114210000.0", 
        "market_cap_usd": "1687902327.0", 
        "available_supply": "114041290.0", 
        "total_supply": "194972068.0", 
        "max_supply": null, 
        "percent_change_1h": "-0.41", 
        "percent_change_24h": "-2.21", 
        "percent_change_7d": "13.97", 
        "last_updated": "1525032855"
    }, 
    {
        "id": "lisk", 
        "name": "Lisk", 
        "symbol": "LSK", 
        "rank": "22", 
        "price_usd": "12.824", 
        "price_btc": "0.00137701", 
        "24h_volume_usd": "41996700.0", 
        "market_cap_usd": "1351269425.0", 
        "available_supply": "105370354.0", 
        "total_supply": "120620748.0", 
        "max_supply": null, 
        "percent_change_1h": "1.39", 
        "percent_change_24h": "8.11", 
        "percent_change_7d": "10.04", 
        "last_updated": "1525032848"
    }, 
    {
        "id": "bitcoin-gold", 
        "name": "Bitcoin Gold", 
        "symbol": "BTG", 
        "rank": "23", 
        "price_usd": "76.6631", 
        "price_btc": "0.00823185", 
        "24h_volume_usd": "46451300.0", 
        "market_cap_usd": "1301223770.0", 
        "available_supply": "16973274.0", 
        "total_supply": "17073274.0", 
        "max_supply": "21000000.0", 
        "percent_change_1h": "-0.23", 
        "percent_change_24h": "0.23", 
        "percent_change_7d": "14.62", 
        "last_updated": "1525032859"
    }, 
    {
        "id": "aeternity", 
        "name": "Aeternity", 
        "symbol": "AE", 
        "rank": "24", 
        "price_usd": "4.86886", 
        "price_btc": "0.0005228", 
        "24h_volume_usd": "136389000.0", 
        "market_cap_usd": "1134544056.0", 
        "available_supply": "233020472.0", 
        "total_supply": "273685830.0", 
        "max_supply": null, 
        "percent_change_1h": "-1.77", 
        "percent_change_24h": "15.97", 
        "percent_change_7d": "106.45", 
        "last_updated": "1525032854"
    }, 
    {
        "id": "zcash", 
        "name": "Zcash", 
        "symbol": "ZEC", 
        "rank": "25", 
        "price_usd": "291.911", 
        "price_btc": "0.0313445", 
        "24h_volume_usd": "62156500.0", 
        "market_cap_usd": "1111857983.0", 
        "available_supply": "3808894.0", 
        "total_supply": "3808894.0", 
        "max_supply": null, 
        "percent_change_1h": "-0.18", 
        "percent_change_24h": "-1.72", 
        "percent_change_7d": "5.7", 
        "last_updated": "1525032851"
    }, 
    {
        "id": "steem", 
        "name": "Steem", 
        "symbol": "STEEM", 
        "rank": "26", 
        "price_usd": "4.20855", 
        "price_btc": "0.0004519", 
        "24h_volume_usd": "32942300.0", 
        "market_cap_usd": "1067635295.0", 
        "available_supply": "253682455.0", 
        "total_supply": "270656549.0", 
        "max_supply": null, 
        "percent_change_1h": "0.34", 
        "percent_change_24h": "-2.33", 
        "percent_change_7d": "36.51", 
        "last_updated": "1525032848"
    }, 
    {
        "id": "verge", 
        "name": "Verge", 
        "symbol": "XVG", 
        "rank": "27", 
        "price_usd": "0.0705792", 
        "price_btc": "0.00000758", 
        "24h_volume_usd": "71657700.0", 
        "market_cap_usd": "1054212725.0", 
        "available_supply": "14936592159.0", 
        "total_supply": "14936592159.0", 
        "max_supply": "16555000000.0", 
        "percent_change_1h": "1.62", 
        "percent_change_24h": "-2.04", 
        "percent_change_7d": "0.61", 
        "last_updated": "1525032845"
    }, 
    {
        "id": "bytom", 
        "name": "Bytom", 
        "symbol": "BTM", 
        "rank": "28", 
        "price_usd": "1.05817", 
        "price_btc": "0.00011362", 
        "24h_volume_usd": "186174000.0", 
        "market_cap_usd": "1044413790.0", 
        "available_supply": "987000000.0", 
        "total_supply": "1407000000.0", 
        "max_supply": null, 
        "percent_change_1h": "0.69", 
        "percent_change_24h": "1.87", 
        "percent_change_7d": "17.04", 
        "last_updated": "1525032856"
    }, 
    {
        "id": "nano", 
        "name": "Nano", 
        "symbol": "NANO", 
        "rank": "29", 
        "price_usd": "7.77496", 
        "price_btc": "0.00083485", 
        "24h_volume_usd": "34162100.0", 
        "market_cap_usd": "1036000119.0", 
        "available_supply": "133248289.0", 
        "total_supply": "133248289.0", 
        "max_supply": "133248290.0", 
        "percent_change_1h": "-0.48", 
        "percent_change_24h": "4.28", 
        "percent_change_7d": "7.27", 
        "last_updated": "1525032853"
    }, 
    {
        "id": "siacoin", 
        "name": "Siacoin", 
        "symbol": "SC", 
        "rank": "30", 
        "price_usd": "0.0289588", 
        "price_btc": "0.00000311", 
        "24h_volume_usd": "83635900.0", 
        "market_cap_usd": "987750489.0", 
        "available_supply": "34108819745.0", 
        "total_supply": "34108819745.0", 
        "max_supply": null, 
        "percent_change_1h": "-0.33", 
        "percent_change_24h": "-2.74", 
        "percent_change_7d": "50.75", 
        "last_updated": "1525032846"
    }, 
    {
        "id": "bytecoin-bcn", 
        "name": "Bytecoin", 
        "symbol": "BCN", 
        "rank": "31", 
        "price_usd": "0.00537195", 
        "price_btc": "0.00000058", 
        "24h_volume_usd": "7234000.0", 
        "market_cap_usd": "987709621.0", 
        "available_supply": "183864261826", 
        "total_supply": "183864261826", 
        "max_supply": "184470000000", 
        "percent_change_1h": "0.44", 
        "percent_change_24h": "-6.9", 
        "percent_change_7d": "10.45", 
        "last_updated": "1525032843"
    }, 
    {
        "id": "ontology", 
        "name": "Ontology", 
        "symbol": "ONT", 
        "rank": "32", 
        "price_usd": "8.63753", 
        "price_btc": "0.00092747", 
        "24h_volume_usd": "328807000.0", 
        "market_cap_usd": "972755674.0", 
        "available_supply": "112619658.0", 
        "total_supply": "1000000000.0", 
        "max_supply": null, 
        "percent_change_1h": "-1.97", 
        "percent_change_24h": "22.76", 
        "percent_change_7d": "110.2", 
        "last_updated": "1525032865"
    }, 
    {
        "id": "populous", 
        "name": "Populous", 
        "symbol": "PPT", 
        "rank": "33", 
        "price_usd": "25.8651", 
        "price_btc": "0.00277731", 
        "24h_volume_usd": "6307540.0", 
        "market_cap_usd": "957112856.0", 
        "available_supply": "37004027.0", 
        "total_supply": "53252246.0", 
        "max_supply": "53252246.0", 
        "percent_change_1h": "1.21", 
        "percent_change_24h": "8.54", 
        "percent_change_7d": "-2.29", 
        "last_updated": "1525032858"
    }, 
    {
        "id": "wanchain", 
        "name": "Wanchain", 
        "symbol": "WAN", 
        "rank": "34", 
        "price_usd": "8.3907", 
        "price_btc": "0.00090097", 
        "24h_volume_usd": "19821700.0", 
        "market_cap_usd": "890693720.0", 
        "available_supply": "106152493.0", 
        "total_supply": "210000000.0", 
        "max_supply": null, 
        "percent_change_1h": "-0.34", 
        "percent_change_24h": "-2.98", 
        "percent_change_7d": "30.09", 
        "last_updated": "1525032866"
    }, 
    {
        "id": "bitcoin-diamond", 
        "name": "Bitcoin Diamond", 
        "symbol": "BCD", 
        "rank": "35", 
        "price_usd": "5.78623", 
        "price_btc": "0.00062131", 
        "24h_volume_usd": "15778900.0", 
        "market_cap_usd": "887426862.0", 
        "available_supply": "153368750.0", 
        "total_supply": "156368750.0", 
        "max_supply": "210000000.0", 
        "percent_change_1h": "-0.34", 
        "percent_change_24h": "-3.89", 
        "percent_change_7d": "29.76", 
        "last_updated": "1525032861"
    }, 
    {
        "id": "bitshares", 
        "name": "BitShares", 
        "symbol": "BTS", 
        "rank": "36", 
        "price_usd": "0.330031", 
        "price_btc": "0.00003544", 
        "24h_volume_usd": "57735600.0", 
        "market_cap_usd": "864704322.0", 
        "available_supply": "2620070000.0", 
        "total_supply": "2620070000.0", 
        "max_supply": "3600570502.0", 
        "percent_change_1h": "-1.35", 
        "percent_change_24h": "17.32", 
        "percent_change_7d": "23.7", 
        "last_updated": "1525032844"
    }, 
    {
        "id": "zilliqa", 
        "name": "Zilliqa", 
        "symbol": "ZIL", 
        "rank": "37", 
        "price_usd": "0.10809", 
        "price_btc": "0.00001161", 
        "24h_volume_usd": "45094900.0", 
        "market_cap_usd": "787328985.0", 
        "available_supply": "7284013186.0", 
        "total_supply": "12600000000.0", 
        "max_supply": null, 
        "percent_change_1h": "0.6", 
        "percent_change_24h": "1.01", 
        "percent_change_7d": "5.36", 
        "last_updated": "1525032864"
    }, 
    {
        "id": "waves", 
        "name": "Waves", 
        "symbol": "WAVES", 
        "rank": "38", 
        "price_usd": "7.12019", 
        "price_btc": "0.00076454", 
        "24h_volume_usd": "132910000.0", 
        "market_cap_usd": "712019000.0", 
        "available_supply": "100000000.0", 
        "total_supply": "100000000.0", 
        "max_supply": null, 
        "percent_change_1h": "0.59", 
        "percent_change_24h": "12.3", 
        "percent_change_7d": "36.2", 
        "last_updated": "1525032848"
    }, 
    {
        "id": "bitcoin-private", 
        "name": "Bitcoin Private", 
        "symbol": "BTCP", 
        "rank": "39", 
        "price_usd": "34.7952", 
        "price_btc": "0.0037362", 
        "24h_volume_usd": "1215180.0", 
        "market_cap_usd": "710502422.0", 
        "available_supply": "20419553.0", 
        "total_supply": "20419553.0", 
        "max_supply": "21000000.0", 
        "percent_change_1h": "-1.56", 
        "percent_change_24h": "-5.26", 
        "percent_change_7d": "-34.3", 
        "last_updated": "1525032866"
    }, 
    {
        "id": "stratis", 
        "name": "Stratis", 
        "symbol": "STRAT", 
        "rank": "40", 
        "price_usd": "7.11862", 
        "price_btc": "0.00076438", 
        "24h_volume_usd": "49771600.0", 
        "market_cap_usd": "703576405.0", 
        "available_supply": "98836067.0", 
        "total_supply": "98836067.0", 
        "max_supply": null, 
        "percent_change_1h": "-1.22", 
        "percent_change_24h": "10.69", 
        "percent_change_7d": "21.74", 
        "last_updated": "1525032849"
    }, 
    {
        "id": "0x", 
        "name": "0x", 
        "symbol": "ZRX", 
        "rank": "41", 
        "price_usd": "1.26072", 
        "price_btc": "0.00013537", 
        "24h_volume_usd": "14242800.0", 
        "market_cap_usd": "662346414.0", 
        "available_supply": "525371545.0", 
        "total_supply": "1000000000.0", 
        "max_supply": null, 
        "percent_change_1h": "0.08", 
        "percent_change_24h": "6.46", 
        "percent_change_7d": "25.21", 
        "last_updated": "1525032856"
    }, 
    {
        "id": "maker", 
        "name": "Maker", 
        "symbol": "MKR", 
        "rank": "42", 
        "price_usd": "1058.38", 
        "price_btc": "0.113646", 
        "24h_volume_usd": "640447.0", 
        "market_cap_usd": "654319907.0", 
        "available_supply": "618228.0", 
        "total_supply": "1000000.0", 
        "max_supply": null, 
        "percent_change_1h": "-0.03", 
        "percent_change_24h": "-1.14", 
        "percent_change_7d": "13.53", 
        "last_updated": "1525032852"
    }, 
    {
        "id": "dogecoin", 
        "name": "Dogecoin", 
        "symbol": "DOGE", 
        "rank": "43", 
        "price_usd": "0.00547434", 
        "price_btc": "0.00000059", 
        "24h_volume_usd": "35593700.0", 
        "market_cap_usd": "625310314.0", 
        "available_supply": "114225699131", 
        "total_supply": "114225699131", 
        "max_supply": null, 
        "percent_change_1h": "1.85", 
        "percent_change_24h": "0.18", 
        "percent_change_7d": "-2.21", 
        "last_updated": "1525032842"
    }, 
    {
        "id": "rchain", 
        "name": "RChain", 
        "symbol": "RHOC", 
        "rank": "44", 
        "price_usd": "1.69516", 
        "price_btc": "0.00018202", 
        "24h_volume_usd": "1407930.0", 
        "market_cap_usd": "609946291.0", 
        "available_supply": "359816354.0", 
        "total_supply": "870663574.0", 
        "max_supply": "1000000000.0", 
        "percent_change_1h": "-3.9", 
        "percent_change_24h": "14.67", 
        "percent_change_7d": "9.75", 
        "last_updated": "1525032858"
    }, 
    {
        "id": "mixin", 
        "name": "Mixin", 
        "symbol": "XIN", 
        "rank": "45", 
        "price_usd": "1448.08", 
        "price_btc": "0.155491", 
        "24h_volume_usd": "1922340.0", 
        "market_cap_usd": "602858419.0", 
        "available_supply": "416316.0", 
        "total_supply": "1000000.0", 
        "max_supply": null, 
        "percent_change_1h": "1.11", 
        "percent_change_24h": "-3.32", 
        "percent_change_7d": "157.67", 
        "last_updated": "1525032863"
    }, 
    {
        "id": "status", 
        "name": "Status", 
        "symbol": "SNT", 
        "rank": "46", 
        "price_usd": "0.17246", 
        "price_btc": "0.00001852", 
        "24h_volume_usd": "145541000.0", 
        "market_cap_usd": "598519634.0", 
        "available_supply": "3470483788.0", 
        "total_supply": "6804870174.0", 
        "max_supply": null, 
        "percent_change_1h": "-0.38", 
        "percent_change_24h": "7.43", 
        "percent_change_7d": "13.08", 
        "last_updated": "1525032854"
    }, 
    {
        "id": "decred", 
        "name": "Decred", 
        "symbol": "DCR", 
        "rank": "47", 
        "price_usd": "82.7521", 
        "price_btc": "0.00888566", 
        "24h_volume_usd": "2515000.0", 
        "market_cap_usd": "591325232.0", 
        "available_supply": "7145743.0", 
        "total_supply": "7565743.0", 
        "max_supply": "21000000.0", 
        "percent_change_1h": "-1.52", 
        "percent_change_24h": "-4.88", 
        "percent_change_7d": "26.82", 
        "last_updated": "1525032848"
    }, 
    {
        "id": "loopring", 
        "name": "Loopring", 
        "symbol": "LRC", 
        "rank": "48", 
        "price_usd": "1.00444", 
        "price_btc": "0.00010785", 
        "24h_volume_usd": "51436400.0", 
        "market_cap_usd": "574614052.0", 
        "available_supply": "572074043.0", 
        "total_supply": "1374956262.0", 
        "max_supply": null, 
        "percent_change_1h": "-0.5", 
        "percent_change_24h": "19.29", 
        "percent_change_7d": "31.83", 
        "last_updated": "1525032856"
    }, 
    {
        "id": "digixdao", 
        "name": "DigixDAO", 
        "symbol": "DGD", 
        "rank": "49", 
        "price_usd": "273.134", 
        "price_btc": "0.0293283", 
        "24h_volume_usd": "6334550.0", 
        "market_cap_usd": "546268000.0", 
        "available_supply": "2000000.0", 
        "total_supply": "2000000.0", 
        "max_supply": null, 
        "percent_change_1h": "0.12", 
        "percent_change_24h": "-0.96", 
        "percent_change_7d": "-3.77", 
        "last_updated": "1525032848"
    }, 
    {
        "id": "hshare", 
        "name": "Hshare", 
        "symbol": "HSR", 
        "rank": "50", 
        "price_usd": "12.1192", 
        "price_btc": "0.00130132", 
        "24h_volume_usd": "86241400.0", 
        "market_cap_usd": "520196940.0", 
        "available_supply": "42923373.0", 
        "total_supply": "42923373.0", 
        "max_supply": "84000000.0", 
        "percent_change_1h": "-0.04", 
        "percent_change_24h": "-6.9", 
        "percent_change_7d": "51.64", 
        "last_updated": "1525032856"
    }, 
    {
        "id": "waltonchain", 
        "name": "Waltonchain", 
        "symbol": "WTC", 
        "rank": "51", 
        "price_usd": "16.3651", 
        "price_btc": "0.00175724", 
        "24h_volume_usd": "7619860.0", 
        "market_cap_usd": "509676301.0", 
        "available_supply": "31144099.0", 
        "total_supply": "70000000.0", 
        "max_supply": "100000000.0", 
        "percent_change_1h": "0.61", 
        "percent_change_24h": "-0.17", 
        "percent_change_7d": "29.84", 
        "last_updated": "1525032856"
    }, 
    {
        "id": "aion", 
        "name": "Aion", 
        "symbol": "AION", 
        "rank": "52", 
        "price_usd": "3.80413", 
        "price_btc": "0.00040847", 
        "24h_volume_usd": "8680660.0", 
        "market_cap_usd": "506228661.0", 
        "available_supply": "133073439.0", 
        "total_supply": "465934587.0", 
        "max_supply": null, 
        "percent_change_1h": "-0.02", 
        "percent_change_24h": "-2.47", 
        "percent_change_7d": "-5.26", 
        "last_updated": "1525032859"
    }, 
    {
        "id": "golem-network-tokens", 
        "name": "Golem", 
        "symbol": "GNT", 
        "rank": "53", 
        "price_usd": "0.586829", 
        "price_btc": "0.00006301", 
        "24h_volume_usd": "25067600.0", 
        "market_cap_usd": "489569135.0", 
        "available_supply": "834262000.0", 
        "total_supply": "1000000000.0", 
        "max_supply": null, 
        "percent_change_1h": "-0.18", 
        "percent_change_24h": "-2.83", 
        "percent_change_7d": "2.27", 
        "last_updated": "1525032850"
    }, 
    {
        "id": "iostoken", 
        "name": "IOStoken", 
        "symbol": "IOST", 
        "rank": "54", 
        "price_usd": "0.0578749", 
        "price_btc": "0.00000621", 
        "24h_volume_usd": "134278000.0", 
        "market_cap_usd": "486149160.0", 
        "available_supply": "8400000000.0", 
        "total_supply": "21000000000.0", 
        "max_supply": null, 
        "percent_change_1h": "-0.06", 
        "percent_change_24h": "5.53", 
        "percent_change_7d": "16.98", 
        "last_updated": "1525032863"
    }, 
    {
        "id": "basic-attention-token", 
        "name": "Basic Attention Token", 
        "symbol": "BAT", 
        "rank": "55", 
        "price_usd": "0.458028", 
        "price_btc": "0.00004918", 
        "24h_volume_usd": "8842890.0", 
        "market_cap_usd": "458028000.0", 
        "available_supply": "1000000000.0", 
        "total_supply": "1500000000.0", 
        "max_supply": null, 
        "percent_change_1h": "0.4", 
        "percent_change_24h": "0.68", 
        "percent_change_7d": "6.92", 
        "last_updated": "1525032855"
    }, 
    {
        "id": "augur", 
        "name": "Augur", 
        "symbol": "REP", 
        "rank": "56", 
        "price_usd": "40.2352", 
        "price_btc": "0.00432033", 
        "24h_volume_usd": "3464480.0", 
        "market_cap_usd": "442587200.0", 
        "available_supply": "11000000.0", 
        "total_supply": "11000000.0", 
        "max_supply": null, 
        "percent_change_1h": "0.02", 
        "percent_change_24h": "-3.8", 
        "percent_change_7d": "-0.48", 
        "last_updated": "1525032847"
    }, 
    {
        "id": "komodo", 
        "name": "Komodo", 
        "symbol": "KMD", 
        "rank": "57", 
        "price_usd": "4.20865", 
        "price_btc": "0.00045191", 
        "24h_volume_usd": "9032360.0", 
        "market_cap_usd": "437923850.0", 
        "available_supply": "104053283.0", 
        "total_supply": "104053283.0", 
        "max_supply": null, 
        "percent_change_1h": "0.3", 
        "percent_change_24h": "6.2", 
        "percent_change_7d": "6.97", 
        "last_updated": "1525032851"
    }, 
    {
        "id": "digibyte", 
        "name": "DigiByte", 
        "symbol": "DGB", 
        "rank": "58", 
        "price_usd": "0.0428744", 
        "price_btc": "0.00000460", 
        "24h_volume_usd": "6881770.0", 
        "market_cap_usd": "436613771.0", 
        "available_supply": "10183554086.0", 
        "total_supply": "10183554086.0", 
        "max_supply": "21000000000.0", 
        "percent_change_1h": "-0.27", 
        "percent_change_24h": "-3.45", 
        "percent_change_7d": "24.17", 
        "last_updated": "1525032850"
    }, 
    {
        "id": "aelf", 
        "name": "aelf", 
        "symbol": "ELF", 
        "rank": "59", 
        "price_usd": "1.65986", 
        "price_btc": "0.00017823", 
        "24h_volume_usd": "187287000.0", 
        "market_cap_usd": "414965000.0", 
        "available_supply": "250000000.0", 
        "total_supply": "280000000.0", 
        "max_supply": "1000000000.0", 
        "percent_change_1h": "0.41", 
        "percent_change_24h": "20.6", 
        "percent_change_7d": "40.44", 
        "last_updated": "1525032862"
    }, 
    {
        "id": "ardor", 
        "name": "Ardor", 
        "symbol": "ARDR", 
        "rank": "60", 
        "price_usd": "0.400042", 
        "price_btc": "0.00004296", 
        "24h_volume_usd": "7140180.0", 
        "market_cap_usd": "399641756.0", 
        "available_supply": "998999495.0", 
        "total_supply": "998999495.0", 
        "max_supply": "998999495.0", 
        "percent_change_1h": "0.05", 
        "percent_change_24h": "0.51", 
        "percent_change_7d": "2.76", 
        "last_updated": "1525032849"
    }, 
    {
        "id": "ark", 
        "name": "Ark", 
        "symbol": "ARK", 
        "rank": "61", 
        "price_usd": "3.85438", 
        "price_btc": "0.00041387", 
        "24h_volume_usd": "3877280.0", 
        "market_cap_usd": "394004691.0", 
        "available_supply": "102222586.0", 
        "total_supply": "133472586.0", 
        "max_supply": null, 
        "percent_change_1h": "0.41", 
        "percent_change_24h": "1.13", 
        "percent_change_7d": "15.2", 
        "last_updated": "1525032852"
    }, 
    {
        "id": "kyber-network", 
        "name": "Kyber Network", 
        "symbol": "KNC", 
        "rank": "62", 
        "price_usd": "2.7774", 
        "price_btc": "0.00029823", 
        "24h_volume_usd": "54963600.0", 
        "market_cap_usd": "372540152.0", 
        "available_supply": "134132697.0", 
        "total_supply": "215625349.0", 
        "max_supply": null, 
        "percent_change_1h": "-0.07", 
        "percent_change_24h": "3.3", 
        "percent_change_7d": "63.74", 
        "last_updated": "1525032857"
    }, 
    {
        "id": "nebulas-token", 
        "name": "Nebulas", 
        "symbol": "NAS", 
        "rank": "63", 
        "price_usd": "9.87977", 
        "price_btc": "0.00106086", 
        "24h_volume_usd": "63092900.0", 
        "market_cap_usd": "350731835.0", 
        "available_supply": "35500000.0", 
        "total_supply": "100000000.0", 
        "max_supply": "100000000.0", 
        "percent_change_1h": "0.0", 
        "percent_change_24h": "12.63", 
        "percent_change_7d": "59.54", 
        "last_updated": "1525032856"
    }, 
    {
        "id": "mithril", 
        "name": "Mithril", 
        "symbol": "MITH", 
        "rank": "64", 
        "price_usd": "1.14744", 
        "price_btc": "0.00012321", 
        "24h_volume_usd": "221821000.0", 
        "market_cap_usd": "350031759.0", 
        "available_supply": "305054520.0", 
        "total_supply": "1000000000.0", 
        "max_supply": null, 
        "percent_change_1h": "0.45", 
        "percent_change_24h": "-5.98", 
        "percent_change_7d": "15.39", 
        "last_updated": "1525032866"
    }, 
    {
        "id": "cortex", 
        "name": "Cortex", 
        "symbol": "CTXC", 
        "rank": "65", 
        "price_usd": "2.26749", 
        "price_btc": "0.00024348", 
        "24h_volume_usd": "91826200.0", 
        "market_cap_usd": "339652901.0", 
        "available_supply": "149792458.0", 
        "total_supply": "299792458.0", 
        "max_supply": null, 
        "percent_change_1h": "-0.35", 
        "percent_change_24h": "30.77", 
        "percent_change_7d": "65.85", 
        "last_updated": "1525032867"
    }, 
    {
        "id": "kucoin-shares", 
        "name": "KuCoin Shares", 
        "symbol": "KCS", 
        "rank": "66", 
        "price_usd": "4.31397", 
        "price_btc": "0.00046322", 
        "24h_volume_usd": "1097630.0", 
        "market_cap_usd": "326699433.0", 
        "available_supply": "75730576.0", 
        "total_supply": "180730576.0", 
        "max_supply": null, 
        "percent_change_1h": "0.21", 
        "percent_change_24h": "-2.82", 
        "percent_change_7d": "2.28", 
        "last_updated": "1525032860"
    }, 
    {
        "id": "pivx", 
        "name": "PIVX", 
        "symbol": "PIVX", 
        "rank": "67", 
        "price_usd": "5.61684", 
        "price_btc": "0.00060312", 
        "24h_volume_usd": "4975890.0", 
        "market_cap_usd": "315065552.0", 
        "available_supply": "56093026.0", 
        "total_supply": "56093026.0", 
        "max_supply": null, 
        "percent_change_1h": "-0.73", 
        "percent_change_24h": "1.85", 
        "percent_change_7d": "0.94", 
        "last_updated": "1525032848"
    }, 
    {
        "id": "monacoin", 
        "name": "MonaCoin", 
        "symbol": "MONA", 
        "rank": "68", 
        "price_usd": "5.21591", 
        "price_btc": "0.00056007", 
        "24h_volume_usd": "4565040.0", 
        "market_cap_usd": "308339823.0", 
        "available_supply": "59115250.0", 
        "total_supply": "59115250.0", 
        "max_supply": null, 
        "percent_change_1h": "-0.45", 
        "percent_change_24h": "-5.25", 
        "percent_change_7d": "29.58", 
        "last_updated": "1525032842"
    }, 
    {
        "id": "gas", 
        "name": "Gas", 
        "symbol": "GAS", 
        "rank": "69", 
        "price_usd": "30.3227", 
        "price_btc": "0.00325595", 
        "24h_volume_usd": "6859240.0", 
        "market_cap_usd": "307119680.0", 
        "available_supply": "10128375.0", 
        "total_supply": "17190378.0", 
        "max_supply": "100000000.0", 
        "percent_change_1h": "-1.43", 
        "percent_change_24h": "10.38", 
        "percent_change_7d": "17.67", 
        "last_updated": "1525032854"
    }, 
    {
        "id": "substratum", 
        "name": "Substratum", 
        "symbol": "SUB", 
        "rank": "70", 
        "price_usd": "0.792534", 
        "price_btc": "0.00008510", 
        "24h_volume_usd": "12151500.0", 
        "market_cap_usd": "303557165.0", 
        "available_supply": "383021000.0", 
        "total_supply": "472000000.0", 
        "max_supply": null, 
        "percent_change_1h": "0.79", 
        "percent_change_24h": "-0.36", 
        "percent_change_7d": "10.39", 
        "last_updated": "1525032857"
    }, 
    {
        "id": "centrality", 
        "name": "Centrality", 
        "symbol": "CENNZ", 
        "rank": "71", 
        "price_usd": "0.441156", 
        "price_btc": "0.00004737", 
        "24h_volume_usd": "263008.0", 
        "market_cap_usd": "303271931.0", 
        "available_supply": "687448275.0", 
        "total_supply": "1200000000.0", 
        "max_supply": null, 
        "percent_change_1h": "-3.35", 
        "percent_change_24h": "-4.48", 
        "percent_change_7d": "7.16", 
        "last_updated": "1525032866"
    }, 
    {
        "id": "qash", 
        "name": "QASH", 
        "symbol": "QASH", 
        "rank": "72", 
        "price_usd": "0.841006", 
        "price_btc": "0.00009030", 
        "24h_volume_usd": "5429330.0", 
        "market_cap_usd": "294352100.0", 
        "available_supply": "350000000.0", 
        "total_supply": "1000000000.0", 
        "max_supply": null, 
        "percent_change_1h": "0.02", 
        "percent_change_24h": "12.8", 
        "percent_change_7d": "7.71", 
        "last_updated": "1525032861"
    }, 
    {
        "id": "syscoin", 
        "name": "Syscoin", 
        "symbol": "SYS", 
        "rank": "73", 
        "price_usd": "0.55098", 
        "price_btc": "0.00005916", 
        "24h_volume_usd": "11909000.0", 
        "market_cap_usd": "293472833.0", 
        "available_supply": "532637905.0", 
        "total_supply": "532637905.0", 
        "max_supply": "888000000.0", 
        "percent_change_1h": "-0.36", 
        "percent_change_24h": "-6.33", 
        "percent_change_7d": "10.85", 
        "last_updated": "1525032844"
    }, 
    {
        "id": "ethos", 
        "name": "Ethos", 
        "symbol": "ETHOS", 
        "rank": "74", 
        "price_usd": "3.6768", 
        "price_btc": "0.0003948", 
        "24h_volume_usd": "11838500.0", 
        "market_cap_usd": "280924816.0", 
        "available_supply": "76404704.0", 
        "total_supply": "222295208.0", 
        "max_supply": null, 
        "percent_change_1h": "-0.22", 
        "percent_change_24h": "3.93", 
        "percent_change_7d": "22.45", 
        "last_updated": "1525032855"
    }, 
    {
        "id": "dragonchain", 
        "name": "Dragonchain", 
        "symbol": "DRGN", 
        "rank": "75", 
        "price_usd": "1.15837", 
        "price_btc": "0.00012438", 
        "24h_volume_usd": "3362760.0", 
        "market_cap_usd": "276180823.0", 
        "available_supply": "238421940.0", 
        "total_supply": "433494437.0", 
        "max_supply": null, 
        "percent_change_1h": "-0.38", 
        "percent_change_24h": "-2.5", 
        "percent_change_7d": "-11.43", 
        "last_updated": "1525032861"
    }, 
    {
        "id": "cryptonex", 
        "name": "Cryptonex", 
        "symbol": "CNX", 
        "rank": "76", 
        "price_usd": "6.09019", 
        "price_btc": "0.00065395", 
        "24h_volume_usd": "1611160.0", 
        "market_cap_usd": "275519919.0", 
        "available_supply": "45239955.0", 
        "total_supply": "106677580.0", 
        "max_supply": "210000000.0", 
        "percent_change_1h": "-2.82", 
        "percent_change_24h": "-4.0", 
        "percent_change_7d": "0.94", 
        "last_updated": "1525032858"
    }, 
    {
        "id": "storm", 
        "name": "Storm", 
        "symbol": "STORM", 
        "rank": "77", 
        "price_usd": "0.0659936", 
        "price_btc": "0.00000709", 
        "24h_volume_usd": "116039000.0", 
        "market_cap_usd": "270026424.0", 
        "available_supply": "4091706234.0", 
        "total_supply": "10000000000.0", 
        "max_supply": null, 
        "percent_change_1h": "0.22", 
        "percent_change_24h": "-2.51", 
        "percent_change_7d": "14.75", 
        "last_updated": "1525032862"
    }, 
    {
        "id": "dentacoin", 
        "name": "Dentacoin", 
        "symbol": "DCN", 
        "rank": "78", 
        "price_usd": "0.000817624", 
        "price_btc": "0.00000009", 
        "24h_volume_usd": "394605.0", 
        "market_cap_usd": "265913084.0", 
        "available_supply": "325226613094", 
        "total_supply": "1963173416169", 
        "max_supply": "8000000000000", 
        "percent_change_1h": "-0.67", 
        "percent_change_24h": "-5.94", 
        "percent_change_7d": "-26.33", 
        "last_updated": "1525032858"
    }, 
    {
        "id": "reddcoin", 
        "name": "ReddCoin", 
        "symbol": "RDD", 
        "rank": "79", 
        "price_usd": "0.00903171", 
        "price_btc": "0.00000097", 
        "24h_volume_usd": "28546600.0", 
        "market_cap_usd": "260191943.0", 
        "available_supply": "28808713174.0", 
        "total_supply": "28808713174.0", 
        "max_supply": null, 
        "percent_change_1h": "-0.71", 
        "percent_change_24h": "0.51", 
        "percent_change_7d": "13.97", 
        "last_updated": "1525032851"
    }, 
    {
        "id": "elastos", 
        "name": "Elastos", 
        "symbol": "ELA", 
        "rank": "80", 
        "price_usd": "50.6302", 
        "price_btc": "0.00543652", 
        "24h_volume_usd": "27970100.0", 
        "market_cap_usd": "259356807.0", 
        "available_supply": "5122571.0", 
        "total_supply": "33462020.0", 
        "max_supply": null, 
        "percent_change_1h": "-0.38", 
        "percent_change_24h": "14.92", 
        "percent_change_7d": "12.85", 
        "last_updated": "1525032864"
    }, 
    {
        "id": "gxchain", 
        "name": "GXChain", 
        "symbol": "GXS", 
        "rank": "81", 
        "price_usd": "4.2978", 
        "price_btc": "0.00046148", 
        "24h_volume_usd": "19547500.0", 
        "market_cap_usd": "257868000.0", 
        "available_supply": "60000000.0", 
        "total_supply": "100000000.0", 
        "max_supply": "100000000.0", 
        "percent_change_1h": "0.89", 
        "percent_change_24h": "9.41", 
        "percent_change_7d": "16.3", 
        "last_updated": "1525032854"
    }, 
    {
        "id": "salt", 
        "name": "SALT", 
        "symbol": "SALT", 
        "rank": "82", 
        "price_usd": "4.43851", 
        "price_btc": "0.00047659", 
        "24h_volume_usd": "16162100.0", 
        "market_cap_usd": "257270654.0", 
        "available_supply": "57963293.0", 
        "total_supply": "120000000.0", 
        "max_supply": null, 
        "percent_change_1h": "1.26", 
        "percent_change_24h": "8.2", 
        "percent_change_7d": "26.77", 
        "last_updated": "1525032858"
    }, 
    {
        "id": "factom", 
        "name": "Factom", 
        "symbol": "FCT", 
        "rank": "83", 
        "price_usd": "28.9621", 
        "price_btc": "0.00310986", 
        "24h_volume_usd": "2471180.0", 
        "market_cap_usd": "253276519.0", 
        "available_supply": "8745102.0", 
        "total_supply": "8745102.0", 
        "max_supply": null, 
        "percent_change_1h": "0.28", 
        "percent_change_24h": "-0.76", 
        "percent_change_7d": "-3.68", 
        "last_updated": "1525032847"
    }, 
    {
        "id": "pundi-x", 
        "name": "Pundi X", 
        "symbol": "NPXS", 
        "rank": "84", 
        "price_usd": "0.00444314", 
        "price_btc": "0.00000048", 
        "24h_volume_usd": "3154730.0", 
        "market_cap_usd": "252999109.0", 
        "available_supply": "56941511923.0", 
        "total_supply": "62845999628.0", 
        "max_supply": null, 
        "percent_change_1h": "-1.15", 
        "percent_change_24h": "-5.8", 
        "percent_change_7d": "-6.4", 
        "last_updated": "1525032866"
    }, 
    {
        "id": "bancor", 
        "name": "Bancor", 
        "symbol": "BNT", 
        "rank": "85", 
        "price_usd": "4.64085", 
        "price_btc": "0.00049832", 
        "24h_volume_usd": "20190000.0", 
        "market_cap_usd": "239882354.0", 
        "available_supply": "51689314.0", 
        "total_supply": "75989904.0", 
        "max_supply": null, 
        "percent_change_1h": "-0.06", 
        "percent_change_24h": "-3.09", 
        "percent_change_7d": "16.62", 
        "last_updated": "1525032854"
    }, 
    {
        "id": "gifto", 
        "name": "Gifto", 
        "symbol": "GTO", 
        "rank": "86", 
        "price_usd": "0.547564", 
        "price_btc": "0.00005880", 
        "24h_volume_usd": "55547900.0", 
        "market_cap_usd": "235287956.0", 
        "available_supply": "429699461.0", 
        "total_supply": "1000000000.0", 
        "max_supply": null, 
        "percent_change_1h": "-0.67", 
        "percent_change_24h": "-3.65", 
        "percent_change_7d": "78.65", 
        "last_updated": "1525032862"
    }, 
    {
        "id": "funfair", 
        "name": "FunFair", 
        "symbol": "FUN", 
        "rank": "87", 
        "price_usd": "0.0472474", 
        "price_btc": "0.00000507", 
        "24h_volume_usd": "6140950.0", 
        "market_cap_usd": "223171827.0", 
        "available_supply": "4723473189.0", 
        "total_supply": "10999873621.0", 
        "max_supply": null, 
        "percent_change_1h": "0.05", 
        "percent_change_24h": "0.78", 
        "percent_change_7d": "-1.14", 
        "last_updated": "1525032854"
    }, 
    {
        "id": "power-ledger", 
        "name": "Power Ledger", 
        "symbol": "POWR", 
        "rank": "88", 
        "price_usd": "0.592317", 
        "price_btc": "0.00006360", 
        "24h_volume_usd": "18758000.0", 
        "market_cap_usd": "216991824.0", 
        "available_supply": "366344076.0", 
        "total_supply": "1000000000.0", 
        "max_supply": null, 
        "percent_change_1h": "0.11", 
        "percent_change_24h": "6.94", 
        "percent_change_7d": "16.26", 
        "last_updated": "1525032859"
    }, 
    {
        "id": "nxt", 
        "name": "Nxt", 
        "symbol": "NXT", 
        "rank": "89", 
        "price_usd": "0.212151", 
        "price_btc": "0.00002278", 
        "24h_volume_usd": "4084600.0", 
        "market_cap_usd": "211938837.0", 
        "available_supply": "998999942.0", 
        "total_supply": "998999942.0", 
        "max_supply": "1000000000.0", 
        "percent_change_1h": "0.42", 
        "percent_change_24h": "-0.47", 
        "percent_change_7d": "4.83", 
        "last_updated": "1525032848"
    }, 
    {
        "id": "zcoin", 
        "name": "ZCoin", 
        "symbol": "XZC", 
        "rank": "90", 
        "price_usd": "45.3336", 
        "price_btc": "0.00486778", 
        "24h_volume_usd": "1898610.0", 
        "market_cap_usd": "210446452.0", 
        "available_supply": "4642174.0", 
        "total_supply": "4642174.0", 
        "max_supply": "21400000.0", 
        "percent_change_1h": "0.92", 
        "percent_change_24h": "-1.41", 
        "percent_change_7d": "3.82", 
        "last_updated": "1525032850"
    }, 
    {
        "id": "wax", 
        "name": "WAX", 
        "symbol": "WAX", 
        "rank": "91", 
        "price_usd": "0.333207", 
        "price_btc": "0.00003578", 
        "24h_volume_usd": "3084420.0", 
        "market_cap_usd": "207181128.0", 
        "available_supply": "621779038.0", 
        "total_supply": "1850000000.0", 
        "max_supply": null, 
        "percent_change_1h": "-0.79", 
        "percent_change_24h": "-6.46", 
        "percent_change_7d": "-3.43", 
        "last_updated": "1525032862"
    }, 
    {
        "id": "veritaseum", 
        "name": "Veritaseum", 
        "symbol": "VERI", 
        "rank": "92", 
        "price_usd": "101.073", 
        "price_btc": "0.0108529", 
        "24h_volume_usd": "1028160.0", 
        "market_cap_usd": "205849865.0", 
        "available_supply": "2036645.0", 
        "total_supply": "100000000.0", 
        "max_supply": null, 
        "percent_change_1h": "1.02", 
        "percent_change_24h": "-5.15", 
        "percent_change_7d": "-20.65", 
        "last_updated": "1525032853"
    }, 
    {
        "id": "enigma-project", 
        "name": "Enigma", 
        "symbol": "ENG", 
        "rank": "93", 
        "price_usd": "2.6885", 
        "price_btc": "0.00028868", 
        "24h_volume_usd": "16085000.0", 
        "market_cap_usd": "201197046.0", 
        "available_supply": "74836171.0", 
        "total_supply": "150000000.0", 
        "max_supply": null, 
        "percent_change_1h": "0.39", 
        "percent_change_24h": "6.29", 
        "percent_change_7d": "5.07", 
        "last_updated": "1525032859"
    }, 
    {
        "id": "neblio", 
        "name": "Neblio", 
        "symbol": "NEBL", 
        "rank": "94", 
        "price_usd": "15.1693", 
        "price_btc": "0.00162883", 
        "24h_volume_usd": "18233100.0", 
        "market_cap_usd": "197931150.0", 
        "available_supply": "13048140.0", 
        "total_supply": "13809045.0", 
        "max_supply": null, 
        "percent_change_1h": "-1.12", 
        "percent_change_24h": "9.63", 
        "percent_change_7d": "30.83", 
        "last_updated": "1525032859"
    }, 
    {
        "id": "fusion", 
        "name": "Fusion", 
        "symbol": "FSN", 
        "rank": "95", 
        "price_usd": "6.43313", 
        "price_btc": "0.00069077", 
        "24h_volume_usd": "7926540.0", 
        "market_cap_usd": "190963162.0", 
        "available_supply": "29684331.0", 
        "total_supply": "57344000.0", 
        "max_supply": null, 
        "percent_change_1h": "-0.22", 
        "percent_change_24h": "7.22", 
        "percent_change_7d": "25.01", 
        "last_updated": "1525032865"
    }, 
    {
        "id": "monaco", 
        "name": "Monaco", 
        "symbol": "MCO", 
        "rank": "96", 
        "price_usd": "11.9951", 
        "price_btc": "0.00128799", 
        "24h_volume_usd": "35320500.0", 
        "market_cap_usd": "189448583.0", 
        "available_supply": "15793831.0", 
        "total_supply": "31587682.0", 
        "max_supply": null, 
        "percent_change_1h": "0.58", 
        "percent_change_24h": "-2.69", 
        "percent_change_7d": "-5.91", 
        "last_updated": "1525032854"
    }, 
    {
        "id": "nucleus-vision", 
        "name": "Nucleus Vision", 
        "symbol": "NCASH", 
        "rank": "97", 
        "price_usd": "0.0451608", 
        "price_btc": "0.00000485", 
        "24h_volume_usd": "40525700.0", 
        "market_cap_usd": "185928578.0", 
        "available_supply": "4117034633.0", 
        "total_supply": "10000000000.0", 
        "max_supply": null, 
        "percent_change_1h": "-0.17", 
        "percent_change_24h": "4.59", 
        "percent_change_7d": "4.13", 
        "last_updated": "1525032866"
    }, 
    {
        "id": "loom-network", 
        "name": "Loom Network", 
        "symbol": "LOOM", 
        "rank": "98", 
        "price_usd": "0.336393", 
        "price_btc": "0.00003612", 
        "24h_volume_usd": "1679460.0", 
        "market_cap_usd": "185882249.0", 
        "available_supply": "552574664.0", 
        "total_supply": "1000000000.0", 
        "max_supply": null, 
        "percent_change_1h": "-0.26", 
        "percent_change_24h": "-1.25", 
        "percent_change_7d": "15.16", 
        "last_updated": "1525032866"
    }, 
    {
        "id": "revain", 
        "name": "Revain", 
        "symbol": "R", 
        "rank": "99", 
        "price_usd": "0.983411", 
        "price_btc": "0.0001056", 
        "24h_volume_usd": "4056410.0", 
        "market_cap_usd": "183356981.0", 
        "available_supply": "186450000.0", 
        "total_supply": "484450000.0", 
        "max_supply": "484450000.0", 
        "percent_change_1h": "0.13", 
        "percent_change_24h": "2.73", 
        "percent_change_7d": "-9.12", 
        "last_updated": "1525032859"
    }, 
    {
        "id": "kin", 
        "name": "Kin", 
        "symbol": "KIN", 
        "rank": "100", 
        "price_usd": "0.000239891", 
        "price_btc": "0.00000003", 
        "24h_volume_usd": "656960.0", 
        "market_cap_usd": "181381000.0", 
        "available_supply": "756097560976", 
        "total_supply": "10000000000000", 
        "max_supply": null, 
        "percent_change_1h": "-0.21", 
        "percent_change_24h": "-7.5", 
        "percent_change_7d": "7.61", 
        "last_updated": "1525032858"
    }
]